elmock/__init__.py
elmock/exception.py
elmock/mocker.py
elmock-1.2.2.dist-info/LICENSE
elmock-1.2.2.dist-info/METADATA
elmock-1.2.2.dist-info/WHEEL
elmock-1.2.2.dist-info/top_level.txt
elmock-1.2.2.dist-info/RECORD
