Metadata-Version: 2.1
Name: elmock
Version: 1.2.2
Summary: A simple package to allow dynamic mocking class definition.
Home-page: https://github.com/elmagician/elmock
Author: Titouan FREVILLE
Author-email: titouan.freville@gmail.com
Project-URL: Bug Tracker, https://github.com/elmagician/elmock/issues
Classifier: Programming Language :: Python :: 3
Classifier: License :: OSI Approved :: GNU General Public License v3 or later (GPLv3+)
Classifier: Operating System :: OS Independent
Requires-Python: >=3.6
License-File: LICENSE
Requires-Dist: pydantic
Requires-Dist: shortuuid
Provides-Extra: dev
Requires-Dist: build ; extra == 'dev'
Requires-Dist: black ; extra == 'dev'
Requires-Dist: bandit ; extra == 'dev'
Requires-Dist: coverage ; extra == 'dev'
Requires-Dist: faker ; extra == 'dev'
Requires-Dist: flake8 ; extra == 'dev'
Requires-Dist: freezegun ; extra == 'dev'
Requires-Dist: isort ; extra == 'dev'
Requires-Dist: mypy ; extra == 'dev'
Requires-Dist: pytest ; extra == 'dev'
Requires-Dist: twine ; extra == 'dev'
Requires-Dist: yoyo-migrations ; extra == 'dev'
